Workbook

Sheet 装箱清单
A1: PACKING LIST 装 箱 清 单
A3: To： | C3: Company: Mekas Automotive Contact: Canice Ugwumba ADD: 186 pacific drive Booral QLD 4655. Australia. TEL: +61406903360 EMAIL: canice.ugwumba@yahoo.com
A4: NO. | B4: PRODUCT PICTURES 产品图片 | C4: DESCRIPTION | E4: HS CODE 海关编码 | F4: Materials 材质 | G4: QUANTITY 箱数 | H4: Number of pieces 每箱件数 | I4: Out packing size &Volum 外箱尺寸和方数 | M4: Weight 毛重(KGS) | N4: Packing Type 包装类型
C5: 英文品名 | D5: 中文品名 | I5: L | J5: M | K5: H | L5: CBM | M5: G.W.
A6: 1 | C6: KUBOTA EXCAVATOR | D6: KUBOTA EXCAVATOR | E6: 8429521990 | G6: 1 | H6: 1 | I6: 0 | J6: 0 | K6: 0 | L6: 0 | M6: 3600 | N6: 纸箱包装
A7: 2 | C7: 200MM BUCKET | D7: 200MM BUCKET | E7: 8431410000 | G7: 1 | H7: 1 | I7: 0 | J7: 0 | K7: 0 | L7: 0 | M7: 25 | N7: 纸箱包装
A8: 3 | C8: 1200MM BUCKET | D8: 1200MM BUCKET | E8: 8431410000 | G8: 1 | H8: 1 | I8: 0 | J8: 0 | K8: 0 | L8: 0 | M8: 130 | N8: 纸箱包装
A9: 4 | C9: RIPPER | D9: RIPPER | E9: 8431499900 | G9: 1 | H9: 1 | I9: 0 | J9: 0 | K9: 0 | L9: 0 | M9: 30 | N9: 纸箱包装
A10: 5 | C10: AUGER | D10: AUGER | E10: 8431499900 | G10: 1 | H10: 1 | I10: 0 | J10: 0 | K10: 0 | L10: 0 | M10: 120 | N10: 纸箱包装
A11: 6 | C11: FORK | D11: FORK | E11: 8431499900 | G11: 1 | H11: 1 | I11: 0 | J11: 0 | K11: 0 | L11: 0 | M11: 45 | N11: 纸箱包装
A12: 7 | C12: 二手挖掘机 | D12: 二手挖掘机 | E12: 8429521990 | G12: 1 | H12: 0 | I12: 0 | J12: 0 | K12: 0 | L12: 0 | M12: 0 | N12: 纸箱包装
A13: 8 | C13: 挖斗 | D13: 挖斗 | E13: 8431410000 | G13: 1 | H13: 0 | I13: 0 | J13: 0 | K13: 0 | L13: 0 | M13: 0 | N13: 纸箱包装
A14: 9 | C14: 松土器 | D14: 松土器 | E14: 8431499900 | G14: 1 | H14: 0 | I14: 0 | J14: 0 | K14: 0 | L14: 0 | M14: 0 | N14: 纸箱包装
A15: 10 | C15: 螺旋钻 | D15: 螺旋钻 | E15: 8431499900 | G15: 1 | H15: 0 | I15: 0 | J15: 0 | K15: 0 | L15: 0 | M15: 0 | N15: 纸箱包装
A16: 11 | C16: 货叉 | D16: 货叉 | E16: 8431499900 | G16: 1 | H16: 0 | I16: 0 | J16: 0 | K16: 0 | L16: 0 | M16: 0 | N16: 纸箱包装
A17: TOTAL: | L17: =SUM(L6:L16) -> 0 | M17: =SUM(M6:M16) -> 3950 | O17: 11 | P17: 6
A19: 包装方式：纸箱包装

Sheet 发票
A1: 商 业 发 票 COMMERCIAL INVOICE
G3: 发 票 号 码 INVOICE NO.
G4: 合 同 号 码 CONTRACT NO.
G5: 日 期 DATE
A6: To： | C6: Company: Mekas Automotive Contact: Canice Ugwumba ADD: 186 pacific drive Booral QLD 4655. Australia. TEL: +61406903360 EMAIL: canice.ugwumba@yahoo.com
A8: NO. | B8: DESCRIPTION | D8: 海关编码 HS CODE | E8: 材质Materials | F8: 外箱数量 Quantity | G8: 每箱件数 Number of pieces | H8: 计价件数 Piece | I8: 出口金额
B9: 英文品名 | C9: 中文品名 | I9: Unit Price | J9: Amont
A10: 1 | B10: KUBOTA EXCAVATOR | C10: KUBOTA EXCAVATOR | D10: 8429521990 | F10: 1 | G10: 1 | H10: 1 | I10: 5300 | J10: 5300
A11: 2 | B11: 200MM BUCKET | C11: 200MM BUCKET | D11: 8431410000 | F11: 1 | G11: 1 | H11: 1 | I11: 150 | J11: 150
A12: 3 | B12: 1200MM BUCKET | C12: 1200MM BUCKET | D12: 8431410000 | F12: 1 | G12: 1 | H12: 1 | I12: 450 | J12: 450
A13: 4 | B13: RIPPER | C13: RIPPER | D13: 8431499900 | F13: 1 | G13: 1 | H13: 1 | I13: 120 | J13: 120
A14: 5 | B14: AUGER | C14: AUGER | D14: 8431499900 | F14: 1 | G14: 1 | H14: 1 | I14: 600 | J14: 600
A15: 6 | B15: FORK | C15: FORK | D15: 8431499900 | F15: 1 | G15: 1 | H15: 1 | I15: 200 | J15: 200
A16: 7 | B16: 二手挖掘机 | C16: 二手挖掘机 | D16: 8429521990 | F16: 1 | G16: 0 | H16: 0 | I16: 5300 | J16: 0
A17: 8 | B17: 挖斗 | C17: 挖斗 | D17: 8431410000 | F17: 1 | G17: 0 | H17: 0 | I17: 150 | J17: 0
A18: 9 | B18: 松土器 | C18: 松土器 | D18: 8431499900 | F18: 1 | G18: 0 | H18: 0 | I18: 120 | J18: 0
A19: 10 | B19: 螺旋钻 | C19: 螺旋钻 | D19: 8431499900 | F19: 1 | G19: 0 | H19: 0 | I19: 600 | J19: 0
A20: 11 | B20: 货叉 | C20: 货叉 | D20: 8431499900 | F20: 1 | G20: 0 | H20: 0 | I20: 200 | J20: 0
B21: TOTAL: | F21: =SUM(F10:F20) -> 11 | H21: =SUM(H10:H20) -> 6 | J21: =SUM(J10:J20) -> 6820

Sheet 申报要素
A1: 申报要素
A2: 合同号: | E2: 目的地: | G2: AUSTRALIA
A3: 日期：
A4: 序号 | B4: 品牌 | C4: 品名 | D4: HS code | E4: 型号 | F4: 材质 | G4: 用途 | H4: 加工工艺 | I4: 适用场景 | J4: 优惠关税 | K4: 产品图
A5: 1 | C5: KUBOTA EXCAVATOR | D5: 8429521990 | J5: ChAFTA 0%
A6: 2 | C6: 200MM BUCKET | D6: 8431410000 | J6: ChAFTA 0%
A7: 3 | C7: 1200MM BUCKET | D7: 8431410000 | J7: ChAFTA 0%
A8: 4 | C8: RIPPER | D8: 8431499900 | J8: ChAFTA 0%
A9: 5 | C9: AUGER | D9: 8431499900 | J9: ChAFTA 0%
A10: 6 | C10: FORK | D10: 8431499900 | J10: ChAFTA 0%
A11: 7 | C11: 二手挖掘机 | D11: 8429521990 | J11: ChAFTA 0%
A12: 8 | C12: 挖斗 | D12: 8431410000 | J12: ChAFTA 0%
A13: 9 | C13: 松土器 | D13: 8431499900 | J13: ChAFTA 0%
A14: 10 | C14: 螺旋钻 | D14: 8431499900 | J14: ChAFTA 0%
A15: 11 | C15: 货叉 | D15: 8431499900 | J15: ChAFTA 0%

Sheet 销货确认书
A1: 销 货 确 认 书
A2: SALES CONFIRMATION
A3: 卖 方 : | C3: 1 | G3: NO.:
A4: SELLERS : | G4: DATE:
A5: 地 址 : | C5: ADD: 186 pacific drive Booral QLD 4655. Australia. | G5: SIGNED AT: | H5: , CHINA
G8: TEL：
G9: Email:
A11: 买 方 ： | B11: BUYERS: | C11: Company: Mekas Automotive Contact: Canice Ugwumba ADD: 186 pacific drive Booral QLD 4655. Australia. TEL: +61406903360 EMAIL: canice.ugwumba@yahoo.com
A12: 地 址 ： | B12: ADDRESS:
A15: 兹经买卖双方同意按下列条款成交:
A16: The undersigned Sellers and Buyers have agreed to choose the following transactions according to the
A17: terms and Conditions stipulated below:
A18: 货号 | C18: 品名及规格 | E18: 数 量 | G18: 单 价 | H18: 金 额
A19: NO. | C19: Description | E19: Quantity | G19: Unit Price | H19: Amount
C20: 品名 | D20: 型号 | F20: CIF | H20: USD
A21: 1 | C21: KUBOTA EXCAVATOR | E21: PCS | F21: 1 | G21: 5300 | H21: 5300
A22: 2 | C22: 200MM BUCKET | E22: PCS | F22: 1 | G22: 150 | H22: 150
A23: 3 | C23: 1200MM BUCKET | E23: PCS | F23: 1 | G23: 450 | H23: 450
A24: 4 | C24: RIPPER | E24: PCS | F24: 1 | G24: 120 | H24: 120
A25: 5 | C25: AUGER | E25: PCS | F25: 1 | G25: 600 | H25: 600
A26: 6 | C26: FORK | E26: PCS | F26: 1 | G26: 200 | H26: 200
A27: 7 | C27: 二手挖掘机 | E27: PCS | F27: 0 | G27: 5300 | H27: 0
A28: 8 | C28: 挖斗 | E28: PCS | F28: 0 | G28: 150 | H28: 0
A29: 9 | C29: 松土器 | E29: PCS | F29: 0 | G29: 120 | H29: 0
A30: 10 | C30: 螺旋钻 | E30: PCS | F30: 0 | G30: 600 | H30: 0
A31: 11 | C31: 货叉 | E31: PCS | F31: 0 | G31: 200 | H31: 0
G32: TOTAL: | H32: =SUM(H21:H31) -> 6820
A33: 3.包 装: | B33: 纸箱包装
A34: 4.装 运 期: | B34: Time of Shipment: On or before: ASAP
A35: 5.装运口岸和目的地:Loading port & Destination：From | E35: CHINA To | F35: AUSTRALIA
A36: 6.保 险:由买方按发票全部金额110%投保至 为止的 险。
A37: Insurance. To be affected by Sellers for 110% of full invoice value covering up to only.
A38: 7.付款条件: | B38: T/T
A39: 8.装船标记: | B39: N/M
A40: Shipping mark:
A41: 9.产 地: | B41: 中 国
A42: The place of origin or production: | D42: CHINA
A43: 10.备 注: | B43: Remarks:
A46: 买 方: | B46: BUYERS: | F46: 卖 方: | G46: SELLERS:

Sheet 报关单 
A1: 中华人民共和国海关出口货物报关单
A4: 预录入编号: | E4: 海关编号: | H4: (XX海关) | O4: 页码/页数: 1/1
A5: 境内发货人 | E5: 出境关别 | H5: 出口日期 | K5: 申报日期 | N5: 备案号
A6: 1
A7: 境外收货人 | E7: 运输方式 | H7: 运输工具名称及航次号 | K7: 提运单号
A8: Company: Mekas Automotive Contact: Canice Ugwumba ADD: 186 pacific drive Booral QLD 4655. Australia. TEL: +61406903360 EMAIL: canice.ugwumba@yahoo.com | E8: 海运
A9: 生产销售单位 | E9: 监管方式 | H9: 征免性质 | K9: 许可证号
A10: =A6 -> 1 | E10: 一般贸易 | H10: 一般征税
A11: 合同协议号 | E11: 贸易国(地区) | H11: 运抵国(地区) | K11: 指运港 | N11: 离境口岸
E12: =销货确认书!F35 -> AUSTRALIA | H12: 澳大利亚 | K12: MELBOURNE | N12: 天津
A13: 包装种类 | E13: 件数 | F13: 毛重(千克) | H13: 净重(千克) | J13: 成交方式 | K13: 运费 | M13: 保费 | O13: 杂费
A14: 纸箱 | E14: 11 | F14: 3950 | H14: 0 | J14: EXW
A15: 随附单证及编号
A16: 发票、装箱单、合同
A17: 标记唛码及备注
A18: N/M
A19: 项号 | B19: 商品编号 | D19: 商品名称及规格型号 | H19: 数量及单位 | J19: 单价/总价/币制 | L19: 原产国(地区) | M19: 最终目的国(地区) | N19: 境内货源地 | P19: 征免
A20: 1 | B20: 8429521990 | D20: =销货确认书!C21 -> KUBOTA EXCAVATOR | H20: PCS | I20: =销货确认书!F21 -> 1 | J20: 5300 | K20: 5300.0 USD | L20: 中国 | M20: AUSTRALIA
A22: 2 | B22: 8431410000 | D22: =销货确认书!C22 -> 200MM BUCKET | H22: PCS | I22: =销货确认书!F22 -> 1 | J22: 150 | K22: 150.0 USD | L22: 中国 | M22: AUSTRALIA
A24: 3 | B24: 8431410000 | D24: =销货确认书!C23 -> 1200MM BUCKET | H24: PCS | I24: =销货确认书!F23 -> 1 | J24: 450 | K24: 450.0 USD | L24: 中国 | M24: AUSTRALIA
A26: 4 | B26: 8431499900 | D26: =销货确认书!C24 -> RIPPER | H26: PCS | I26: =销货确认书!F24 -> 1 | J26: 120 | K26: 120.0 USD | L26: 中国 | M26: AUSTRALIA
A28: 5 | B28: 8431499900 | D28: =销货确认书!C25 -> AUGER | H28: PCS | I28: =销货确认书!F25 -> 1 | J28: 600 | K28: 600.0 USD | L28: 中国 | M28: AUSTRALIA
A30: 6 | B30: 8431499900 | D30: =销货确认书!C26 -> FORK | H30: PCS | I30: =销货确认书!F26 -> 1 | J30: 200 | K30: 200.0 USD | L30: 中国 | M30: AUSTRALIA
A32: 7 | B32: 8429521990 | D32: =销货确认书!C27 -> 二手挖掘机 | H32: PCS | I32: =销货确认书!F27 -> 0 | J32: 5300 | K32: 0.0 USD | L32: 中国 | M32: AUSTRALIA
A34: 8 | B34: 8431410000 | D34: =销货确认书!C28 -> 挖斗 | H34: PCS | I34: =销货确认书!F28 -> 0 | J34: 150 | K34: 0.0 USD | L34: 中国 | M34: AUSTRALIA
A36: 9 | B36: 8431499900 | D36: =销货确认书!C29 -> 松土器 | H36: PCS | I36: =销货确认书!F29 -> 0 | J36: 120 | K36: 0.0 USD | L36: 中国 | M36: AUSTRALIA
A38: 10 | B38: 8431499900 | D38: =销货确认书!C30 -> 螺旋钻 | H38: PCS | I38: =销货确认书!F30 -> 0 | J38: 600 | K38: 0.0 USD | L38: 中国 | M38: AUSTRALIA
A40: 11 | B40: 8431499900 | D40: =销货确认书!C31 -> 货叉 | H40: PCS | I40: =销货确认书!F31 -> 0 | J40: 200 | K40: 0.0 USD | L40: 中国 | M40: AUSTRALIA
A44: 报关人员 | C44: 报关人员证号 | E44: 电话 | G44: 兹申明对以上内容承担如实申报、依法纳税之法律责任 | M44: 海关批注及签章
A46: 申报单位 | H46: 申报单位（签章）
